syn/axi_fifo.sv
`timescale 1ns / 1ps

module axi_fifo #(
    parameter int WIDTH = 32,
    parameter int DEPTH = 16   // Must be a power of 2
) (
    input  logic             aclk,
    input  logic             aresetn,
    // Write Port (Push)
    input  logic [WIDTH-1:0] data_in,
    input  logic             push,
    output logic             full,
    // Read Port (Pop)
    output logic [WIDTH-1:0] data_out,
    input  logic             pop,
    output logic             empty
);

    // 1. Calculate pointer width: log2(DEPTH) + 1 for the wrap bit
    localparam PTR_W = $clog2(DEPTH) + 1;

    // 2. Storage Array
    logic [WIDTH-1:0] mem[DEPTH-1];

    // 3. Pointers
    logic [PTR_W-1:0] wr_ptr, rd_ptr;

    // 4. Status Flags
    // Empty: All bits match
    assign empty = (wr_ptr == rd_ptr);
    // Full: Index bits match, but MSB (wrap bit) is different
    assign full  = (wr_ptr[PTR_W-2:0] == rd_ptr[PTR_W-2:0]) && (wr_ptr[PTR_W-1] != rd_ptr[PTR_W-1]);

    // 5. Read/Write Logic
    always_ff @(posedge aclk) begin
        if (!aresetn) begin
            wr_ptr <= '0;
            rd_ptr <= '0;
        end else begin
            // Write when pushed and not full
            if (push && !full) begin
                mem[wr_ptr[PTR_W-2:0]] <= data_in;
                wr_ptr <= wr_ptr + 1'b1;
            end
            // Read when popped and not empty
            if (pop && !empty) begin
                rd_ptr <= rd_ptr + 1'b1;
            end
        end
    end

    // Continuous assignment for output data (pointing to current head)
    assign data_out = mem[rd_ptr[PTR_W-2:0]];
endmodule

sim/fifo_tb.sv
`timescale 1ns / 1ps

module fifo_tb;
  parameter DATA_WIDTH = 64;  // System address bus width

  logic aclk = 0;
  logic aresetn;
  logic [(DATA_WIDTH-1):0] data_in;
  logic push;
  logic pop;
  logic fifo_full;
  logic [(DATA_WIDTH-1):0] data_out;
  logic fifo_empty;

  // Clock generation (100MHz)
  always #5 aclk = ~aclk;


  // logic [10:0] mem_test[99:0];
  // logic mem_test[99:0];

  axi_fifo #(
      .WIDTH(DATA_WIDTH),
      .DEPTH(4)
  ) fifo_i (
      .aclk(aclk),
      .aresetn(aresetn),

      .data_in(data_in),
      .push(push),
      .full(fifo_full),

      .data_out(data_out),
      .pop(pop),
      .empty(fifo_empty)
  );

  // Simple integrity check in Icarus
  logic [(DATA_WIDTH-1):0] local_queue[$];  // SystemVerilog queue

  always @(posedge aclk) begin
    if (pop && !fifo_full) local_queue.push_back(data_in);
    if (push && !fifo_empty) begin
      logic [(DATA_WIDTH-1):0] expected;  // Standard declaration
      expected = local_queue.pop_front();
      if (data_out !== expected)
        $display("ERROR: Mismatch! Got %h, Expected %h", data_out, expected);
    end
  end

  initial begin
    aresetn = 0;
    push = 0;
    pop = 0;

    #10 aresetn = 1;

    push_word(64'h41234567890abcd1);
    push_word(64'h41234567890abcd2);
    push_word(64'h41234567890abcd3);
    pop <= 1;
    push_word(64'h41234567890abcd4);
    push_word(64'h41234567890abcd5);
    push_word(64'h41234567890abcd5);
    pop <= 0;
    push_word(64'h41234567890abcd6);
    push_word(64'h01234567890abcd7);

    push_word(64'h01234567890abcd8);
    push_word(64'h01234567890abcd9);
    push_word(64'h01234567890abcda);

    for (int i = 0; i < 8; i++) begin
      pop_word();
    end

    #50 $finish;
  end

  task push_word(input [(DATA_WIDTH-1):0] b);
    @(posedge aclk);
    data_in <= b;  // Use <= instead of =
    push    <= 1;  // Use <= instead of =
    @(posedge aclk);  // Wait for the NEXT edge to bring it low
    push <= 0;
  endtask

  task pop_word();
    @(posedge aclk);
    pop <= 1;
    @(posedge aclk);
    pop <= 0;
  endtask

endmodule

dump.vcd
$date
	Wed Mar  4 20:07:11 2026
$end
$version
	Icarus Verilog
$end
$timescale
	1ps
$end
$scope module fifo_tb $end
$scope module fifo_i $end
$var reg 8 ! \mem[0] [7:0] $end
$upscope $end
$upscope $end
$scope module fifo_tb $end
$var wire 1 " fifo_full $end
$var wire 1 # fifo_empty $end
$var wire 8 $ data_out [7:0] $end
$var parameter 32 % DATA_WIDTH $end
$var reg 1 & aclk $end
$var reg 1 ' aresetn $end
$var reg 8 ( data_in [7:0] $end
$var reg 1 ) pop $end
$var reg 1 * push $end
$scope module fifo_i $end
$var wire 1 & aclk $end
$var wire 1 ' aresetn $end
$var wire 8 + data_in [7:0] $end
$var wire 8 , data_out [7:0] $end
$var wire 1 " full $end
$var wire 1 ) pop $end
$var wire 1 * push $end
$var wire 1 # empty $end
$var parameter 32 - DEPTH $end
$var parameter 33 . PTR_W $end
$var parameter 32 / WIDTH $end
$var reg 3 0 rd_ptr [2:0] $end
$var reg 3 1 wr_ptr [2:0] $end
$upscope $end
$scope task pop_byte $end
$upscope $end
$scope task push_byte $end
$var reg 8 2 b [7:0] $end
$upscope $end
$upscope $end
$scope module dump_trigger $end
$upscope $end
$enddefinitions $end
$comment Show the parameter values. $end
$dumpall
b1000 /
b11 .
b100 -
b1000 %
$end
#0
$dumpvars
bx 2
bx 1
bx 0
bx ,
bx +
0*
0)
bx (
0'
0&
bx $
x#
x"
bx !
$end
#5000
0"
1#
b0 0
b0 1
1&
#10000
0&
#15000
1&
#20000
0&
b1000001 2
1'
#25000
0#
b1 1
b1000001 !
b1000001 $
b1000001 ,
1*
b1000001 (
b1000001 +
1&
#30000
0&
#35000
b10 1
1&
1*
#40000
0&
#45000
b11 1
1&
1*
#50000
0&
#55000
1"
b100 1
1&
1*
#60000
0&
#65000
b1000010 (
b1000010 +
1&
b1000010 2
1*
#70000
0&
#75000
1&
1*
#80000
0&
#85000
b1000011 (
b1000011 +
1&
b1000011 2
1*
#90000
0&
#95000
b0 (
b0 +
1&
b0 2
1*
#100000
0&
#105000
0"
b1 0
1&
1)
0*
#110000
0&
#115000
b10 0
1&
#120000
0&
#125000
b11 0
1&
#130000
0&
#135000
1#
b100 0
1&
